nilsolve/__init__.py
nilsolve/api.py
nilsolve/cli.py
nilsolve/examples.py
nilsolve/loaders.py
nilsolve/metrics.py
nilsolve/models.py
nilsolve/plot2d.py
nilsolve/plotting.py
nilsolve/scan.py
nilsolve/scan2d.py
nilsolve/spec.py
nilsolve/core/budget.py
nilsolve/core/decision.py
nilsolve/core/evaluate_proc.py
nilsolve/core/io.py
nilsolve/core/plotting.py
nilsolve/core/quality.py
nilsolve/core/cont/__init__.py
nilsolve/core/cont/arclength.py
nilsolve/core/cont/detect.py
nilsolve/core/cont/io.py
nilsolve/core/cont/newton.py
nilsolve/core/cont/numdiff.py
nilsolve/core/cont/plotting.py
nilsolve/core/cont/run.py
nilsolve/core/cont/spec.py
nilsolve/core/cont/stability.py
nilsolve-0.1.0.dist-info/METADATA
nilsolve-0.1.0.dist-info/WHEEL
nilsolve-0.1.0.dist-info/entry_points.txt
nilsolve-0.1.0.dist-info/top_level.txt
nilsolve-0.1.0.dist-info/RECORD
